celus_nibbler/__init__.py
celus_nibbler/__main__.py
celus_nibbler/aggregator.py
celus_nibbler/conditions.py
celus_nibbler/coordinates.py
celus_nibbler/data_headers.py
celus_nibbler/definitions/__init__.py
celus_nibbler/definitions/base.py
celus_nibbler/definitions/celus_format.py
celus_nibbler/definitions/counter.py
celus_nibbler/definitions/generic.py
celus_nibbler/eat_and_poop.py
celus_nibbler/errors.py
celus_nibbler/parsers/__init__.py
celus_nibbler/parsers/base.py
celus_nibbler/parsers/counter/__init__.py
celus_nibbler/parsers/counter/c4.py
celus_nibbler/parsers/counter/c5.py
celus_nibbler/parsers/counter/c51.py
celus_nibbler/parsers/counter/c51json.py
celus_nibbler/parsers/counter/c5json.py
celus_nibbler/parsers/dynamic.py
celus_nibbler/parsers/non_counter/__init__.py
celus_nibbler/parsers/non_counter/base.py
celus_nibbler/parsers/non_counter/celus_format.py
celus_nibbler/parsers/non_counter/generic.py
celus_nibbler/reader.py
celus_nibbler/sources.py
celus_nibbler/utils.py
celus_nibbler/validators.py
celus_nibbler-13.0.0.dist-info/WHEEL
celus_nibbler-13.0.0.dist-info/entry_points.txt
celus_nibbler-13.0.0.dist-info/METADATA
celus_nibbler-13.0.0.dist-info/RECORD
