Metadata-Version: 2.4
Name: celus-nibbler
Version: 13.0.0
Summary: Counter-like data reader and processor.
Keywords: parsing,counter5
Author: Stepan Henek, Zbynek Vyhlas
Author-email: Stepan Henek <stepan@bigdigdata.com>, Zbynek Vyhlas <zbyneksmail@gmail.com>
License-Expression: MIT
Classifier: Programming Language :: Python :: 3
Classifier: Topic :: Software Development :: Libraries
Requires-Dist: celus-nigiri>=5.0.0,<6
Requires-Dist: diskcache~=5.6.0
Requires-Dist: nltk~=3.9.1
Requires-Dist: pydantic~=2.12.5
Requires-Dist: python-dateutil~=2.9.0
Requires-Dist: openpyxl~=3.1.2
Requires-Dist: unidecode~=1.4.0
Requires-Dist: isbnlib~=3.10.14
Requires-Dist: typing-extensions~=4.15.0
Requires-Dist: xlrd~=2.0.2 ; extra == 'xls'
Requires-Python: >=3.12, <4
Project-URL: Documentation, https://gitlab.com/big-dig-data/celus-nibbler/-/blob/master/README.md
Provides-Extra: xls
